LICENSE
MANIFEST.in
README.rst
setup.py
geokey_export/__init__.py
geokey_export/base.py
geokey_export/models.py
geokey_export/renderers.py
geokey_export/urls.py
geokey_export/utils.py
geokey_export/views.py
geokey_export.egg-info/PKG-INFO
geokey_export.egg-info/SOURCES.txt
geokey_export.egg-info/dependency_links.txt
geokey_export.egg-info/top_level.txt
geokey_export/migrations/0001_initial.py
geokey_export/migrations/0002_export_isoneoff.py
geokey_export/migrations/0003_export_urlhash.py
geokey_export/migrations/0004_export_bounding_box.py
geokey_export/migrations/__init__.py
geokey_export/static/js/admin.ui.export.js
geokey_export/templates/export_access.html
geokey_export/templates/export_breadcrumb.html
geokey_export/templates/export_create.html
geokey_export/templates/export_header.html
geokey_export/templates/export_index.html
geokey_export/templates/export_overview.html
geokey_export/templatetags/__init__.py
geokey_export/templatetags/export_tags.py