Metadata-Version: 1.1
Name: geokey-export
Version: 0.4.1
Summary: Export data from GeoKey to KML or GeoJSON
Home-page: https://github.com/ExCiteS/geokey-export
Author: ExCiteS
Author-email: excites@ucl.ac.uk
License: MIT
Download-URL: https://github.com/ExCiteS/geokey-export/tarball/0.4.1
Platform: UNKNOWN
